position_tools/__init__.py
position_tools/core.py
position_tools/video.py
position_tools-0.2.2.dist-info/LICENSE
position_tools-0.2.2.dist-info/METADATA
position_tools-0.2.2.dist-info/WHEEL
position_tools-0.2.2.dist-info/top_level.txt
position_tools-0.2.2.dist-info/RECORD
