Metadata-Version: 2.1
Name: position_tools
Version: 0.2.2
Home-page: 
Author: 
Author-email: 
License: MIT
License-File: LICENSE
Requires-Dist: numpy >=1.11
Requires-Dist: scipy
Requires-Dist: tqdm
